capirs/__init__.py
capirs/detect_adv.py
capirs/image_processing.py
capirs-0.1.dist-info/METADATA
capirs-0.1.dist-info/RECORD
capirs-0.1.dist-info/WHEEL
capirs-0.1.dist-info/top_level.txt
