Metadata-Version: 2.1
Name: capirs
Version: 0.1
Summary: Detect adversarial images
Home-page: https://github.com/ajbradberry96/SeniorDesignCAPIRS
Author: Tertia Oculus
Author-email: chrizrodz@gmail.com
License: MIT
Platform: UNKNOWN
